pix2pixhd/__init__.py
pix2pixhd/encode_features.py
pix2pixhd/precompute_feature_maps.py
pix2pixhd/run_engine.py
pix2pixhd/test.py
pix2pixhd/train.py
pix2pixhd/data/__init__.py
pix2pixhd/data/aligned_dataset.py
pix2pixhd/data/base_data_loader.py
pix2pixhd/data/base_dataset.py
pix2pixhd/data/custom_dataset_data_loader.py
pix2pixhd/data/data_loader.py
pix2pixhd/data/image_folder.py
pix2pixhd/models/__init__.py
pix2pixhd/models/base_model.py
pix2pixhd/models/models.py
pix2pixhd/models/networks.py
pix2pixhd/models/pix2pixHD_model.py
pix2pixhd/models/ui_model.py
pix2pixhd/options/__init__.py
pix2pixhd/options/base_options.py
pix2pixhd/options/test_options.py
pix2pixhd/options/train_options.py
pix2pixhd/util/__init__.py
pix2pixhd/util/html.py
pix2pixhd/util/image_pool.py
pix2pixhd/util/util.py
pix2pixhd/util/visualizer.py
pix2pixhd-1.0.dist-info/LICENSE.txt
pix2pixhd-1.0.dist-info/METADATA
pix2pixhd-1.0.dist-info/WHEEL
pix2pixhd-1.0.dist-info/entry_points.txt
pix2pixhd-1.0.dist-info/top_level.txt
pix2pixhd-1.0.dist-info/RECORD
