Metadata-Version: 2.1
Name: pix2pixhd
Version: 1.0
Summary: Synthesizing and manipulating 2048x1024 images with conditional GANs
Home-page: https://github.com/NVIDIA/pix2pixHD
Author: Ting-Chun Wang, Ming-Yu Liu, Jun-Yan Zhu, Andrew Tao, Jan Kautz, Bryan Catanzaro
Author-email: tingchunw@nvidia.com, mingyul@nvidia.com, jan@jankautz.com, junyanz@cs.cmu.edu, bcatanzaro@acm.org
License: BSD
Platform: UNKNOWN
Requires-Dist: dominate (>=2.4.0)
Requires-Dist: numpy
Requires-Dist: pillow
Requires-Dist: scikit-learn
Requires-Dist: torch (>=1.4.0)
Requires-Dist: torchvision (>=0.5.0)
